datacatalog/__init__.py
datacatalog/agavehelpers.py
datacatalog/basestore.py
datacatalog/challenges.py
datacatalog/configs.py
datacatalog/constants.py
datacatalog/dicthelpers.py
datacatalog/exceptions.py
datacatalog/experiments.py
datacatalog/filesfixity.py
datacatalog/filesmetadata.py
datacatalog/logstore.py
datacatalog/main.py
datacatalog/measurements.py
datacatalog/mongo.py
datacatalog/posixhelpers.py
datacatalog/samples.py
datacatalog/utils.py
datacatalog/identifiers/__init__.py
datacatalog/identifiers/abaco_hashid.py
datacatalog/identifiers/agave_appid.py
datacatalog/identifiers/datacatalog_uuid.py
datacatalog/identifiers/interesting_animal.py
datacatalog/jobs/__init__.py
datacatalog/jobs/agavejobs.py
datacatalog/jobs/fsm.py
datacatalog/jobs/graphfsm.py
datacatalog/jobs/job.py
datacatalog/jobs/main.py
datacatalog/jobs/store.py
datacatalog/jobs/token.py
datacatalog/jobs/utils.py
datacatalog/pipelinejobs/__init__.py
datacatalog/pipelinejobs/pipelinejob.py
datacatalog/pipelines/__init__.py
datacatalog/pipelines/store.py
datacatalog/pipelines/token.py
datacatalog/pipelines/utils.py
datacatalog-0.1.4.dist-info/METADATA
datacatalog-0.1.4.dist-info/RECORD
datacatalog-0.1.4.dist-info/WHEEL
datacatalog-0.1.4.dist-info/top_level.txt
