Metadata-Version: 2.1
Name: datacatalog
Version: 0.1.4
Summary: Python package implementing essential logic for SD2 Data Catalog
Home-page: https://github.com/SD2E/python-datacatalog
Author: Matthew Vaughn
Author-email: opensource@sd2e.org
License: BSD
Platform: UNKNOWN
Classifier: Programming Language :: Python :: 3.6
Classifier: Programming Language :: Python :: 3
Classifier: Programming Language :: Python :: 2.7
Classifier: License :: OSI Approved :: BSD License
Classifier: Operating System :: OS Independent
Classifier: Development Status :: 4 - Beta
Classifier: Intended Audience :: Developers
Classifier: Natural Language :: English
Requires-Dist: agavepy (>=0.7.3)
Requires-Dist: PyMongo (>=3.7.1)
Requires-Dist: attrdict (>=2.0.0)
Requires-Dist: jsondiff (>=1.1.2)
Requires-Dist: filetype (>=1.0.1)
Requires-Dist: transitions (>=0.6.8)
Requires-Dist: jsonschema (>=2.6.0)
Requires-Dist: hashids (>=1.2.0)
Requires-Dist: petname (>=2.2)
Requires-Dist: python-slugify (>=1.2.5)
